src/__init__.py
src/client.py
src/config.py
src/mcp_server.py
src/models.py
src/server.py
src/tools.py
src/tools/__init__.py
src/tools/assessment_tools.py
src/tools/event_tools.py
src/tools/misc_tools.py
src/tools/property_tools.py
src/tools/sale_tools.py
src/tools/school_tools.py
src/tools/valuation_tools.py
mcp_server_attom-0.0.12.dist-info/METADATA
mcp_server_attom-0.0.12.dist-info/WHEEL
mcp_server_attom-0.0.12.dist-info/entry_points.txt
mcp_server_attom-0.0.12.dist-info/RECORD
