Metadata-Version: 2.4
Name: mcp-server-attom
Version: 0.0.12
Summary: MCP server for the ATTOM Real Estate API
Project-URL: Homepage, https://github.com/nkbud/mcp-server-attom
Project-URL: Bug Tracker, https://github.com/nkbud/mcp-server-attom/issues
Project-URL: Documentation, https://github.com/nkbud/mcp-server-attom#readme
Author-email: Nicholas Budzban <nicholasbudzban@gmail.com>
Keywords: api,attom,mcp,property,real-estate,uvx
Classifier: Intended Audience :: Developers
Classifier: Operating System :: OS Independent
Classifier: Programming Language :: Python :: 3
Classifier: Programming Language :: Python :: 3.11
Classifier: Topic :: Software Development :: Libraries :: Python Modules
Requires-Python: >=3.11
Requires-Dist: fastmcp>=0.4.0
Requires-Dist: httpx
Requires-Dist: pydantic>=2.0.0
Requires-Dist: python-dotenv
Requires-Dist: structlog
Provides-Extra: dev
Requires-Dist: black; extra == 'dev'
Requires-Dist: isort; extra == 'dev'
Requires-Dist: ruff; extra == 'dev'
Provides-Extra: test
Requires-Dist: pytest; extra == 'test'
Requires-Dist: pytest-asyncio; extra == 'test'
Requires-Dist: pytest-cov; extra == 'test'
Requires-Dist: pyyaml; extra == 'test'
Requires-Dist: respx; extra == 'test'
